Workbook

Sheet Q&A Engine
A1: LOCUS · PSYCHOMETRIC SCORING ENGINE · 25-QUESTION INSTRUMENT
A2: Holland (RIASEC) · Big Five (OCEAN) · Self-Determination Theory · Multiple Intelligences · Career Decision-Making
A4: SCORE COLUMNS → H = Holland RIASEC | O = Big Five OCEAN | S = Self-Determination Theory | M = Multiple Intelligences | D = Decision-Making Readiness
A5: Q# | B5: Question / Scenario | C5: Answer Option | D5: H | E5: O | F5: S | G5: M | H5: D | I5: Theory Focus | J5: Construct Measured
A6: 1 | B6: Your college fest committee needs volunteers. Which role do you sign up for without hesitation? | C6: A — Set up and manage the stage equipment and sound system | D6: 5 | E6: 1 | F6: 3 | G6: 2 | H6: 2 | I6: Holland | J6: Realistic (R)
C7: B — Research and design the event theme with data from past fests | D7: 2 | E7: 4 | F7: 4 | G7: 3 | H7: 3 | I7: Holland + SDT | J7: Investigative (I) + Autonomy
C8: C — Coordinate all volunteers, make sure everyone has a role | D8: 2 | E8: 3 | F8: 4 | G8: 5 | H8: 4 | I8: Holland + MI | J8: Social (S) + Interpersonal Intel
C9: D — Promote the fest on social media and design creatives | D9: 3 | E9: 2 | F9: 3 | G9: 4 | H9: 3 | I9: Holland | J9: Artistic (A)
C10: E — Handle registrations, budget tracking, and vendor payments | D10: 2 | E10: 4 | F10: 2 | G10: 2 | H10: 4 | I10: Holland | J10: Conventional (C)
A11: 2 | B11: You have a major exam in 3 weeks and a club event happening this weekend. What do you actually do? | C11: A — Skip the event, start studying immediately with a fixed schedule | D11: 2 | E11: 5 | F11: 2 | G11: 2 | H11: 5 | I11: Big Five | J11: Conscientiousness (High)
C12: B — Attend the event but study every other day leading up to the exam | D12: 3 | E12: 3 | F12: 3 | G12: 3 | H12: 3 | I12: Big Five | J12: Conscientiousness (Mid)
C13: C — Attend the event and cram the night before the exam | D13: 4 | E13: 1 | F13: 2 | G13: 3 | H13: 1 | I13: Big Five | J13: Conscientiousness (Low)
C14: D — Delegate your club responsibilities to someone else so you can prepare | D14: 3 | E14: 4 | F14: 4 | G14: 3 | H14: 4 | I14: Big Five + SDT | J14: Conscientiousness + Competence
A15: 3 | B15: You get two internship offers. Offer A pays ₹25,000/month in a field you find boring. Offer B pays ₹8,000 in a field that genuinely interests you. What do you pick? | C15: A — Offer A. Money now is more important | D15: 2 | E15: 3 | F15: 1 | G15: 2 | H15: 3 | I15: SDT | J15: Extrinsic Motivation
C16: B — Offer B. The learning matters more than the pay at this stage | D16: 4 | E16: 3 | F16: 5 | G16: 4 | H16: 4 | I16: SDT | J16: Intrinsic Motivation + Autonomy
C17: C — Negotiate Offer B's pay upward before deciding | D17: 3 | E17: 4 | F17: 4 | G17: 3 | H17: 5 | I17: SDT + CDM | J17: Autonomy + Decision-Making
C18: D — Ask family, then decide based on their input | D18: 2 | E18: 2 | F18: 2 | G18: 2 | H18: 2 | I18: SDT | J18: Extrinsic + Relatedness low
A19: 4 | B19: A friend describes their startup idea to you. What's the first thing your mind does? | C19: A — Start calculating if the numbers actually work — market size, costs, margins | D19: 2 | E19: 5 | F19: 3 | G19: 1 | H19: 4 | I19: MI | J19: Logical-Mathematical
C20: B — Think about how to tell the story to investors or customers | D20: 3 | E20: 2 | F20: 3 | G20: 5 | H20: 3 | I20: MI | J20: Linguistic
C21: C — Visualise the product — what it looks like, how it flows | D21: 3 | E21: 2 | F21: 3 | G21: 4 | H21: 3 | I21: MI | J21: Spatial
C22: D — Immediately think about the team — who's needed, what roles | D22: 2 | E22: 3 | F22: 4 | G22: 5 | H22: 3 | I22: MI | J22: Interpersonal
C23: E — Ask whether this idea actually solves a real human problem | D23: 4 | E23: 3 | F23: 5 | G23: 3 | H23: 4 | I23: MI + SDT | J23: Intrapersonal + Competence
A24: 5 | B24: You're given free time and a small budget of ₹5,000. You most naturally… | C24: A — Start a small resale or service business to turn a profit | D24: 5 | E24: 3 | F24: 4 | G24: 3 | H24: 4 | I24: Holland | J24: Enterprising (E)
C25: B — Use it to attend a skill workshop or online course | D25: 3 | E25: 4 | F25: 4 | G25: 3 | H25: 4 | I25: Holland + SDT | J25: Investigative + Competence
C26: C — Organise a community event or help someone in need | D26: 2 | E26: 3 | F26: 3 | G26: 5 | H26: 3 | I26: Holland | J26: Social (S)
C27: D — Spend it on art supplies, music gear, or creative tools | D27: 3 | E27: 1 | F27: 4 | G27: 4 | H27: 2 | I27: Holland | J27: Artistic (A)
A28: 6 | B28: Your professor gives a completely unconventional assignment — no rules, just 'submit something meaningful'. You feel… | C28: A — Excited. This is when I do my best work | D28: 5 | E28: 4 | F28: 5 | G28: 5 | H28: 3 | I28: Big Five | J28: Openness (High)
C29: B — Curious but a little anxious — you'll work through it | D29: 4 | E29: 3 | F29: 4 | G29: 4 | H29: 3 | I29: Big Five | J29: Openness (Mid-High)
C30: C — Frustrated. You prefer clear guidelines and rubrics | D30: 2 | E30: 5 | F30: 2 | G30: 2 | H30: 4 | I30: Big Five | J30: Openness (Low)
C31: D — Indifferent. You'll just do the minimum needed to pass | D31: 1 | E31: 2 | F31: 1 | G31: 2 | H31: 2 | I31: Big Five | J31: Low engagement
A32: 7 | B32: When someone asks you 'what do you want to do after graduation?', you typically… | C32: A — Have a clear, specific answer with a plan already in motion | D32: 4 | E32: 4 | F32: 5 | G32: 4 | H32: 5 | I32: CDM | J32: Crystallization stage
C33: B — Have a few options you're seriously considering but haven't decided | D33: 4 | E33: 3 | F33: 4 | G33: 4 | H33: 4 | I33: CDM | J33: Exploration stage
C34: C — Give a vague answer because you genuinely haven't thought deeply about it | D34: 2 | E34: 2 | F34: 2 | G34: 2 | H34: 2 | I34: CDM | J34: Pre-contemplation
C35: D — Get anxious — you worry you're behind everyone else | D35: 2 | E35: 2 | F35: 2 | G35: 2 | H35: 1 | I35: CDM | J35: Decision paralysis
A36: 8 | B36: You have to explain a complex topic to your class. You instinctively create… | C36: A — A visual diagram, infographic, or sketch | D36: 3 | E36: 2 | F36: 4 | G36: 5 | H36: 3 | I36: MI | J36: Spatial Intelligence
C37: B — A well-structured written explanation with examples | D37: 4 | E37: 3 | F37: 3 | G37: 5 | H37: 3 | I37: MI | J37: Linguistic Intelligence
C38: C — A live demonstration or hands-on activity | D38: 4 | E38: 2 | F38: 4 | G38: 3 | H38: 3 | I38: MI | J38: Bodily-Kinesthetic
C39: D — A story or analogy that makes it relatable | D39: 3 | E39: 2 | F39: 4 | G39: 4 | H39: 3 | I39: MI | J39: Linguistic + Interpersonal
C40: E — A spreadsheet or data breakdown | D40: 2 | E40: 5 | F40: 3 | G40: 1 | H40: 4 | I40: MI | J40: Logical-Mathematical
A41: 9 | B41: Your ideal study or work environment is… | C41: A — A busy café or co-working space with ambient noise | D41: 4 | E41: 2 | F41: 3 | G41: 3 | H41: 3 | I41: Big Five | J41: Extraversion (High)
C42: B — A quiet room, alone, with no distractions | D42: 2 | E42: 5 | F42: 3 | G42: 2 | H42: 4 | I42: Big Five | J42: Extraversion (Low) / Introversion
C43: C — A small group of 2-3 people you trust | D43: 3 | E43: 3 | F43: 3 | G43: 4 | H43: 3 | I43: Big Five | J43: Ambiversion
C44: D — Wherever the deadline pressure pushes you | D44: 2 | E44: 2 | F44: 2 | G44: 2 | H44: 2 | I44: Big Five | J44: Low self-regulation
A45: 10 | B45: Which of these statements feels most true for you right now? | C45: A — I know exactly what I'm good at and I build on those strengths | D45: 4 | E45: 4 | F45: 5 | G45: 4 | H45: 5 | I45: SDT | J45: Competence (High)
C46: B — I'm still figuring out where my strengths really lie | D46: 3 | E46: 3 | F46: 3 | G46: 3 | H46: 3 | I46: SDT | J46: Competence (Developing)
C47: C — I feel like others are more capable than me in most areas | D47: 1 | E47: 2 | F47: 1 | G47: 2 | H47: 1 | I47: SDT | J47: Competence (Low)
C48: D — I'm good at many things but nothing stands out | D48: 3 | E48: 3 | F48: 3 | G48: 3 | H48: 3 | I48: SDT | J48: Competence (Diffuse)
A49: 11 | B49: You're watching a documentary. You're most drawn to content about… | C49: A — How diseases spread and how the body fights back | D49: 3 | E49: 5 | F49: 4 | G49: 3 | H49: 3 | I49: Holland + MI | J49: Investigative + Naturalistic
C50: B — How a startup went from zero to billion-dollar company | D50: 5 | E50: 3 | F50: 4 | G50: 3 | H50: 4 | I50: Holland | J50: Enterprising (E)
C51: C — How ancient civilisations built structures we still can't replicate | D51: 4 | E51: 4 | F51: 4 | G51: 4 | H51: 3 | I51: Holland + MI | J51: Investigative + Spatial
C52: D — How a director creates emotional impact through filmmaking | D52: 4 | E52: 2 | F52: 4 | G52: 5 | H52: 2 | I52: Holland + MI | J52: Artistic + Spatial/Linguistic
C53: E — How policy changes affect millions of people across a country | D53: 3 | E53: 3 | F53: 4 | G53: 4 | H53: 4 | I53: Holland | J53: Social (S)
A54: 12 | B54: A teammate is consistently not pulling their weight on a group project. You… | C54: A — Confront them directly and clearly explain the impact on the team | D54: 3 | E54: 4 | F54: 4 | G54: 3 | H54: 4 | I54: Big Five | J54: Agreeableness (Low-Mid) + Assertive
C55: B — Take on their work to avoid conflict and keep the project on track | D55: 2 | E55: 4 | F55: 2 | G55: 3 | H55: 3 | I55: Big Five | J55: Agreeableness (High) + Avoidant
C56: C — Talk to them privately, try to understand what's going wrong | D56: 2 | E56: 4 | F56: 4 | G56: 5 | H56: 4 | I56: Big Five + SDT | J56: Agreeableness + Relatedness
C57: D — Report it to the professor or group leader | D57: 3 | E57: 4 | F57: 2 | G57: 2 | H57: 3 | I57: Big Five | J57: Rule-following / Conventional
A58: 13 | B58: When learning something new, you absorb it best when you… | C58: A — Actually do it — build it, perform it, make it with your hands | D58: 5 | E58: 2 | F58: 4 | G58: 2 | H58: 3 | I58: MI | J58: Bodily-Kinesthetic
C59: B — Read about it deeply and take detailed notes | D59: 2 | E59: 5 | F59: 3 | G59: 3 | H59: 4 | I59: MI | J59: Linguistic + Logical
C60: C — Watch a video or observe someone doing it first | D60: 3 | E60: 3 | F60: 3 | G60: 4 | H60: 3 | I60: MI | J60: Spatial + Visual
C61: D — Discuss it with someone else to test your understanding | D61: 3 | E61: 3 | F61: 4 | G61: 5 | H61: 4 | I61: MI | J61: Interpersonal
C62: E — Map it out in a diagram or framework before diving in | D62: 2 | E62: 5 | F62: 3 | G62: 3 | H62: 4 | I62: MI | J62: Logical-Mathematical + Spatial
A63: 14 | B63: A random conversation at a family event gives you an unexpected opportunity in a field you'd never considered. You… | C63: A — Get excited and follow up on it immediately | D63: 5 | E63: 3 | F63: 5 | G63: 4 | H63: 5 | I63: CDM | J63: Happenstance readiness (High)
C64: B — Think about it seriously before making any move | D64: 4 | E64: 4 | F64: 4 | G64: 3 | H64: 4 | I64: CDM | J64: Deliberate exploration
C65: C — Dismiss it — it doesn't fit your current plan | D65: 2 | E65: 4 | F65: 2 | G65: 2 | H65: 3 | I65: CDM | J65: Closed to happenstance
C66: D — Mention it to family to see if they approve first | D66: 2 | E66: 2 | F66: 2 | G66: 2 | H66: 2 | I66: CDM + SDT | J66: External locus + low autonomy
A67: 15 | B67: You're at your most energised and 'in flow' when you are… | C67: A — Teaching, mentoring, or explaining something to someone | D67: 2 | E67: 3 | F67: 4 | G67: 5 | H67: 4 | I67: Holland + MI | J67: Social + Interpersonal
C68: B — Solving a puzzle, debugging a problem, or figuring out how something works | D68: 3 | E68: 5 | F68: 4 | G68: 2 | H68: 4 | I68: Holland + MI | J68: Investigative + Logical
C69: C — Creating something — writing, designing, composing | D69: 4 | E69: 2 | F69: 5 | G69: 5 | H69: 3 | I69: Holland + MI | J69: Artistic + Spatial/Linguistic
C70: D — Persuading people or negotiating a deal | D70: 5 | E70: 3 | F70: 4 | G70: 3 | H70: 4 | I70: Holland | J70: Enterprising (E)
C71: E — Executing a process efficiently and getting things done correctly | D71: 3 | E71: 5 | F71: 3 | G71: 2 | H71: 4 | I71: Holland | J71: Conventional (C)
A72: 16 | B72: Before a high-stakes presentation or performance, you typically feel… | C72: A — Calm and prepared — pressure is just part of the process | D72: 4 | E72: 5 | F72: 4 | G72: 4 | H72: 5 | I72: Big Five | J72: Low Neuroticism / High Stability
C73: B — Nervous but it pushes you to perform better | D73: 4 | E73: 3 | F73: 4 | G73: 3 | H73: 4 | I73: Big Five | J73: Mid Neuroticism (adaptive)
C74: C — Extremely anxious — it significantly affects your performance | D74: 2 | E74: 2 | F74: 2 | G74: 2 | H74: 2 | I74: Big Five | J74: High Neuroticism
C75: D — Indifferent — you don't overthink these things | D75: 3 | E75: 3 | F75: 3 | G75: 3 | H75: 3 | I75: Big Five | J75: Low investment
A76: 17 | B76: Which of these describes why you want to be successful in your chosen career? | C76: A — I want to become genuinely good at something that matters to me | D76: 4 | E76: 4 | F76: 5 | G76: 4 | H76: 5 | I76: SDT | J76: Intrinsic — Mastery
C77: B — I want financial security and a stable, respected life | D77: 2 | E77: 3 | F77: 2 | G77: 2 | H77: 3 | I77: SDT | J77: Extrinsic — Status/Security
C78: C — I want my family to be proud of what I've achieved | D78: 2 | E78: 3 | F78: 2 | G78: 3 | H78: 3 | I78: SDT | J78: Extrinsic — Social approval
C79: D — I want to solve a real problem or contribute to something bigger | D79: 4 | E79: 3 | F79: 5 | G79: 4 | H79: 4 | I79: SDT | J79: Intrinsic — Purpose
A80: 18 | B80: Which of these tasks would you actually enjoy doing as part of your regular work? | C80: A — Analysing large datasets to find patterns or insights | D80: 2 | E80: 5 | F80: 3 | G80: 1 | H80: 4 | I80: Holland + MI | J80: Investigative + Logical-Math
C81: B — Managing and coordinating a team's workflow and timelines | D81: 3 | E81: 4 | F81: 3 | G81: 4 | H81: 4 | I81: Holland | J81: Enterprising + Conventional
C82: C — Designing visuals, user interfaces, or creative content | D82: 4 | E82: 2 | F82: 4 | G82: 5 | H82: 3 | I82: Holland + MI | J82: Artistic + Spatial
C83: D — Conducting lab work, experiments, or technical analysis | D83: 4 | E83: 4 | F83: 3 | G83: 2 | H83: 3 | I83: Holland | J83: Realistic + Investigative
C84: E — Writing reports, policies, documentation, or proposals | D84: 3 | E84: 4 | F84: 3 | G84: 4 | H84: 4 | I84: Holland + MI | J84: Conventional + Linguistic
A85: 19 | B85: When researching a major life decision (college, career, city to move to), you… | C85: A — Go deep — read everything, talk to people in that field, build a spreadsheet | D85: 3 | E85: 5 | F85: 4 | G85: 3 | H85: 5 | I85: CDM | J85: Systematic decision-making
C86: B — Do a quick search, trust your gut, and move on | D86: 4 | E86: 2 | F86: 4 | G86: 3 | H86: 3 | I86: CDM | J86: Intuitive decision-making
C87: C — Ask people you trust and mostly go with their advice | D87: 2 | E87: 3 | F87: 2 | G87: 3 | H87: 2 | I87: CDM | J87: Dependent decision-making
C88: D — Delay until the deadline forces a decision | D88: 2 | E88: 2 | F88: 2 | G88: 2 | H88: 1 | I88: CDM | J88: Avoidant decision-making
A89: 20 | B89: Which of these elective subjects would you have genuinely loved in school? | C89: A — Music theory and composition | D89: 3 | E89: 2 | F89: 4 | G89: 5 | H89: 2 | I89: MI | J89: Musical Intelligence
C90: B — Environmental science and ecology | D90: 3 | E90: 4 | F90: 4 | G90: 4 | H90: 3 | I90: MI | J90: Naturalistic Intelligence
C91: C — Physical education, sports science, or dance | D91: 5 | E91: 2 | F91: 4 | G91: 3 | H91: 2 | I91: MI | J91: Bodily-Kinesthetic
C92: D — Computer science and programming | D92: 2 | E92: 5 | F92: 3 | G92: 2 | H92: 4 | I92: MI + Holland | J92: Logical-Math + Investigative
C93: E — Psychology and human behaviour | D93: 3 | E93: 3 | F93: 4 | G93: 5 | H93: 4 | I93: MI + Holland | J93: Interpersonal + Social
A94: 21 | B94: You have a business idea you genuinely believe in. The only way to test it is to spend ₹20,000 of your savings. You… | C94: A — Do it immediately — the only way to know is to try | D94: 5 | E94: 2 | F94: 5 | G94: 3 | H94: 4 | I94: Holland + Big Five | J94: Enterprising + Openness
C95: B — Build a scaled-down version to test first with minimal investment | D95: 4 | E95: 4 | F95: 5 | G95: 3 | H95: 5 | I95: Holland + CDM | J95: Enterprising + Systematic
C96: C — Wait until you have more certainty before spending money | D96: 2 | E96: 4 | F96: 2 | G96: 2 | H96: 3 | I96: Big Five | J96: High Conscientiousness / Risk-averse
C97: D — Look for a co-founder to share the financial risk | D97: 3 | E97: 3 | F97: 4 | G97: 4 | H97: 4 | I97: SDT + Holland | J97: Relatedness + Enterprising
A98: 22 | B98: Your parents strongly prefer you pursue a specific career. You want something different. You… | C98: A — Follow your own path and explain your reasoning to them over time | D98: 4 | E98: 3 | F98: 5 | G98: 4 | H98: 5 | I98: SDT | J98: Autonomy (High)
C99: B — Try to find a middle ground that satisfies both sides | D99: 3 | E99: 3 | F99: 4 | G99: 3 | H99: 4 | I99: SDT | J99: Autonomy (Mid)
C100: C — Agree to their preference to avoid conflict, even if unhappy | D100: 1 | E100: 2 | F100: 1 | G100: 2 | H100: 1 | I100: SDT | J100: Autonomy (Low) / Controlled motivation
C101: D — Delay the decision and hope the situation resolves itself | D101: 2 | E101: 2 | F101: 2 | G101: 2 | H101: 1 | I101: SDT + CDM | J101: Low autonomy + avoidant
...

Sheet Student Calculator
A1: LOCUS — STUDENT RESPONSE SHEET & COMPOSITE CAREER FIT CALCULATOR
A2: INSTRUCTIONS: For each question, paste or type the scores from the Q&A Engine sheet for the option the student selected.
A3: Q# | B3: Student Selected Answer (paste option text) | C3: Holland (H) | D3: OCEAN (O) | E3: SDT (S) | F3: MI (M) | G3: CDM (D)
A4: 1 | B4: [Paste student's answer here] | C4: 0 | D4: 0 | E4: 0 | F4: 0 | G4: 0
A5: 2 | B5: [Paste student's answer here] | C5: 0 | D5: 0 | E5: 0 | F5: 0 | G5: 0
A6: 3 | B6: [Paste student's answer here] | C6: 0 | D6: 0 | E6: 0 | F6: 0 | G6: 0
A7: 4 | B7: [Paste student's answer here] | C7: 0 | D7: 0 | E7: 0 | F7: 0 | G7: 0
A8: 5 | B8: [Paste student's answer here] | C8: 0 | D8: 0 | E8: 0 | F8: 0 | G8: 0
A9: 6 | B9: [Paste student's answer here] | C9: 0 | D9: 0 | E9: 0 | F9: 0 | G9: 0
A10: 7 | B10: [Paste student's answer here] | C10: 0 | D10: 0 | E10: 0 | F10: 0 | G10: 0
A11: 8 | B11: [Paste student's answer here] | C11: 0 | D11: 0 | E11: 0 | F11: 0 | G11: 0
A12: 9 | B12: [Paste student's answer here] | C12: 0 | D12: 0 | E12: 0 | F12: 0 | G12: 0
A13: 10 | B13: [Paste student's answer here] | C13: 0 | D13: 0 | E13: 0 | F13: 0 | G13: 0
A14: 11 | B14: [Paste student's answer here] | C14: 0 | D14: 0 | E14: 0 | F14: 0 | G14: 0
A15: 12 | B15: [Paste student's answer here] | C15: 0 | D15: 0 | E15: 0 | F15: 0 | G15: 0
... A28: 25 | B28: [Paste student's answer here] | C28: 0 | D28: 0 | E28: 0 | F28: 0 | G28: 0
A29: TOTAL | B29: Raw Score (max 125 per theory) | C29: =SUM(C4:C28) -> 0 | D29: =SUM(D4:D28) -> 0 | E29: =SUM(E4:E28) -> 0 | F29: =SUM(F4:F28) -> 0 | G29: =SUM(G4:G28) -> 0
A30: SCORE % | B30: Normalised 0–100 per theory (÷125 × 100) | C30: =ROUND(C29/125*100,1) -> 0.0% | D30: =ROUND(D29/125*100,1) -> 0.0% | E30: =ROUND(E29/125*100,1) -> 0.0% | F30: =ROUND(F29/125*100,1) -> 0.0% | G30: =ROUND(G29/125*100,1) -> 0.0%
A32: COMPOSITE CAREER FIT SCORE (CCFS) — THE MASTER FORMULA
A33: CCFS Formula: | C33: =(C30*0.25 + D30*0.2 + E30*0.25 + F30*0.2 + G30*0.1) -> 0
A34: CCFS Result: | C34: =ROUND(C30*0.25 + D30*0.2 + E30*0.25 + F30*0.2 + G30*0.1, 1) -> 0
A35: WEIGHTS: Holland 25% | OCEAN 20% | SDT 25% | MI 20% | CDM 10%
A36: Motivation Quality Override: If SDT score < 50, apply 0.85× multiplier to CCFS (extrinsic motivation risk flag)
A37: Adjusted CCFS (with SDT flag): | C37: =IF(E30<50, ROUND(C34*0.85,1), C34) -> 0

Sheet Career Match Engine
A1: LOCUS — 127 CAREER PATH MATCHING ENGINE
A2: Each career has a SUCCESS PROFILE (expected scores). Delta = |Student Score − Success Profile|. Lower delta = better fit.
A3: # | B3: Career Path | C3: Domain | D3: H✓ | E3: O✓ | F3: S✓ | G3: M✓ | H3: D✓ | I3: Δ Holland | J3: Δ OCEAN | K3: Δ SDT | L3: Δ MI | M3: Fit Score (100) | N3: Status
A4: 1 | B4: Medical Doctor (MBBS→MD) | C4: Medicine | D4: 85 | E4: 75 | F4: 80 | G4: 70 | H4: 80 | I4: =ABS('Student Calculator'!C30-D4) -> 85 | J4: =ABS('Student Calculator'!D30-E4) -> 75 | K4: =ABS('Student Calculator'!E30-F4) -> 80 | L4: =ABS('Student Calculator'!F30-G4) -> 70 | M4: =ROUND(MAX(0, 100 - (I4*0.25 + J4*0.2 + K4*0.25 + L4*0.2)), 1) -> 29.8 | N4: =IF(M4>=72,"🟢 BEST FIT",IF(M4>=52,"🟡 CONSIDER","🔴 MISMATCH")) -> 🔴 MISMATCH
A5: 2 | B5: Surgeon | C5: Medicine | D5: 85 | E5: 80 | F5: 75 | G5: 75 | H5: 80 | I5: =ABS('Student Calculator'!C30-D5) -> 85 | J5: =ABS('Student Calculator'!D30-E5) -> 80 | K5: =ABS('Student Calculator'!E30-F5) -> 75 | L5: =ABS('Student Calculator'!F30-G5) -> 75 | M5: =ROUND(MAX(0, 100 - (I5*0.25 + J5*0.2 + K5*0.25 + L5*0.2)), 1) -> 29 | N5: =IF(M5>=72,"🟢 BEST FIT",IF(M5>=52,"🟡 CONSIDER","🔴 MISMATCH")) -> 🔴 MISMATCH
A6: 3 | B6: Dentist | C6: Medicine | D6: 80 | E6: 75 | F6: 75 | G6: 70 | H6: 75 | I6: =ABS('Student Calculator'!C30-D6) -> 80 | J6: =ABS('Student Calculator'!D30-E6) -> 75 | K6: =ABS('Student Calculator'!E30-F6) -> 75 | L6: =ABS('Student Calculator'!F30-G6) -> 70 | M6: =ROUND(MAX(0, 100 - (I6*0.25 + J6*0.2 + K6*0.25 + L6*0.2)), 1) -> 32.3 | N6: =IF(M6>=72,"🟢 BEST FIT",IF(M6>=52,"🟡 CONSIDER","🔴 MISMATCH")) -> 🔴 MISMATCH
A7: 4 | B7: Pharmacist | C7: Medicine | D7: 70 | E7: 80 | F7: 70 | G7: 65 | H7: 75 | I7: =ABS('Student Calculator'!C30-D7) -> 70 | J7: =ABS('Student Calculator'!D30-E7) -> 80 | K7: =ABS('Student Calculator'!E30-F7) -> 70 | L7: =ABS('Student Calculator'!F30-G7) -> 65 | M7: =ROUND(MAX(0, 100 - (I7*0.25 + J7*0.2 + K7*0.25 + L7*0.2)), 1) -> 36 | N7: =IF(M7>=72,"🟢 BEST FIT",IF(M7>=52,"🟡 CONSIDER","🔴 MISMATCH")) -> 🔴 MISMATCH
A8: 5 | B8: Biomedical Researcher | C8: Research | D8: 60 | E8: 90 | F8: 80 | G8: 65 | H8: 80 | I8: =ABS('Student Calculator'!C30-D8) -> 60 | J8: =ABS('Student Calculator'!D30-E8) -> 90 | K8: =ABS('Student Calculator'!E30-F8) -> 80 | L8: =ABS('Student Calculator'!F30-G8) -> 65 | M8: =ROUND(MAX(0, 100 - (I8*0.25 + J8*0.2 + K8*0.25 + L8*0.2)), 1) -> 34 | N8: =IF(M8>=72,"🟢 BEST FIT",IF(M8>=52,"🟡 CONSIDER","🔴 MISMATCH")) -> 🔴 MISMATCH
A9: 6 | B9: Geneticist | C9: Research | D9: 55 | E9: 90 | F9: 80 | G9: 60 | H9: 80 | I9: =ABS('Student Calculator'!C30-D9) -> 55 | J9: =ABS('Student Calculator'!D30-E9) -> 90 | K9: =ABS('Student Calculator'!E30-F9) -> 80 | L9: =ABS('Student Calculator'!F30-G9) -> 60 | M9: =ROUND(MAX(0, 100 - (I9*0.25 + J9*0.2 + K9*0.25 + L9*0.2)), 1) -> 36.3 | N9: =IF(M9>=72,"🟢 BEST FIT",IF(M9>=52,"🟡 CONSIDER","🔴 MISMATCH")) -> 🔴 MISMATCH
A10: 7 | B10: Microbiologist | C10: Research | D10: 55 | E10: 85 | F10: 80 | G10: 60 | H10: 75 | I10: =ABS('Student Calculator'!C30-D10) -> 55 | J10: =ABS('Student Calculator'!D30-E10) -> 85 | K10: =ABS('Student Calculator'!E30-F10) -> 80 | L10: =ABS('Student Calculator'!F30-G10) -> 60 | M10: =ROUND(MAX(0, 100 - (I10*0.25 + J10*0.2 + K10*0.25 + L10*0.2)), 1) -> 37.3 | N10: =IF(M10>=72,"🟢 BEST FIT",IF(M10>=52,"🟡 CONSIDER","🔴 MISMATCH")) -> 🔴 MISMATCH
A11: 8 | B11: Biochemist | C11: Research | D11: 55 | E11: 85 | F11: 80 | G11: 60 | H11: 75 | I11: =ABS('Student Calculator'!C30-D11) -> 55 | J11: =ABS('Student Calculator'!D30-E11) -> 85 | K11: =ABS('Student Calculator'!E30-F11) -> 80 | L11: =ABS('Student Calculator'!F30-G11) -> 60 | M11: =ROUND(MAX(0, 100 - (I11*0.25 + J11*0.2 + K11*0.25 + L11*0.2)), 1) -> 37.3 | N11: =IF(M11>=72,"🟢 BEST FIT",IF(M11>=52,"🟡 CONSIDER","🔴 MISMATCH")) -> 🔴 MISMATCH
A12: 9 | B12: Neuroscientist | C12: Research | D12: 55 | E12: 90 | F12: 85 | G12: 60 | H12: 80 | I12: =ABS('Student Calculator'!C30-D12) -> 55 | J12: =ABS('Student Calculator'!D30-E12) -> 90 | K12: =ABS('Student Calculator'!E30-F12) -> 85 | L12: =ABS('Student Calculator'!F30-G12) -> 60 | M12: =ROUND(MAX(0, 100 - (I12*0.25 + J12*0.2 + K12*0.25 + L12*0.2)), 1) -> 35 | N12: =IF(M12>=72,"🟢 BEST FIT",IF(M12>=52,"🟡 CONSIDER","🔴 MISMATCH")) -> 🔴 MISMATCH
A13: 10 | B13: Clinical Psychologist | C13: Psychology | D13: 45 | E13: 70 | F13: 85 | G13: 75 | H13: 80 | I13: =ABS('Student Calculator'!C30-D13) -> 45 | J13: =ABS('Student Calculator'!D30-E13) -> 70 | K13: =ABS('Student Calculator'!E30-F13) -> 85 | L13: =ABS('Student Calculator'!F30-G13) -> 75 | M13: =ROUND(MAX(0, 100 - (I13*0.25 + J13*0.2 + K13*0.25 + L13*0.2)), 1) -> 38.5 | N13: =IF(M13>=72,"🟢 BEST FIT",IF(M13>=52,"🟡 CONSIDER","🔴 MISMATCH")) -> 🔴 MISMATCH
A14: 11 | B14: Psychiatrist | C14: Psychology | D14: 50 | E14: 75 | F14: 85 | G14: 70 | H14: 80 | I14: =ABS('Student Calculator'!C30-D14) -> 50 | J14: =ABS('Student Calculator'!D30-E14) -> 75 | K14: =ABS('Student Calculator'!E30-F14) -> 85 | L14: =ABS('Student Calculator'!F30-G14) -> 70 | M14: =ROUND(MAX(0, 100 - (I14*0.25 + J14*0.2 + K14*0.25 + L14*0.2)), 1) -> 37.3 | N14: =IF(M14>=72,"🟢 BEST FIT",IF(M14>=52,"🟡 CONSIDER","🔴 MISMATCH")) -> 🔴 MISMATCH
A15: 12 | B15: Physiotherapist | C15: Medicine | D15: 80 | E15: 65 | F15: 75 | G15: 75 | H15: 70 | I15: =ABS('Student Calculator'!C30-D15) -> 80 | J15: =ABS('Student Calculator'!D30-E15) -> 65 | K15: =ABS('Student Calculator'!E30-F15) -> 75 | L15: =ABS('Student Calculator'!F30-G15) -> 75 | M15: =ROUND(MAX(0, 100 - (I15*0.25 + J15*0.2 + K15*0.25 + L15*0.2)), 1) -> 33.3 | N15: =IF(M15>=72,"🟢 BEST FIT",IF(M15>=52,"🟡 CONSIDER","🔴 MISMATCH")) -> 🔴 MISMATCH
A16: 13 | B16: Occupational Therapist | C16: Medicine | D16: 75 | E16: 65 | F16: 75 | G16: 75 | H16: 70 | I16: =ABS('Student Calculator'!C30-D16) -> 75 | J16: =ABS('Student Calculator'!D30-E16) -> 65 | K16: =ABS('Student Calculator'!E30-F16) -> 75 | L16: =ABS('Student Calculator'!F30-G16) -> 75 | M16: =ROUND(MAX(0, 100 - (I16*0.25 + J16*0.2 + K16*0.25 + L16*0.2)), 1) -> 34.5 | N16: =IF(M16>=72,"🟢 BEST FIT",IF(M16>=52,"🟡 CONSIDER","🔴 MISMATCH")) -> 🔴 MISMATCH
A17: 14 | B17: Nutritionist/Dietitian | C17: Medicine | D17: 65 | E17: 70 | F17: 75 | G17: 65 | H17: 70 | I17: =ABS('Student Calculator'!C30-D17) -> 65 | J17: =ABS('Student Calculator'!D30-E17) -> 70 | K17: =ABS('Student Calculator'!E30-F17) -> 75 | L17: =ABS('Student Calculator'!F30-G17) -> 65 | M17: =ROUND(MAX(0, 100 - (I17*0.25 + J17*0.2 + K17*0.25 + L17*0.2)), 1) -> 38 | N17: =IF(M17>=72,"🟢 BEST FIT",IF(M17>=52,"🟡 CONSIDER","🔴 MISMATCH")) -> 🔴 MISMATCH
A18: 15 | B18: Veterinarian | C18: Medicine | D18: 80 | E18: 70 | F18: 75 | G18: 65 | H18: 70 | I18: =ABS('Student Calculator'!C30-D18) -> 80 | J18: =ABS('Student Calculator'!D30-E18) -> 70 | K18: =ABS('Student Calculator'!E30-F18) -> 75 | L18: =ABS('Student Calculator'!F30-G18) -> 65 | M18: =ROUND(MAX(0, 100 - (I18*0.25 + J18*0.2 + K18*0.25 + L18*0.2)), 1) -> 34.3 | N18: =IF(M18>=72,"🟢 BEST FIT",IF(M18>=52,"🟡 CONSIDER","🔴 MISMATCH")) -> 🔴 MISMATCH
A19: 16 | B19: Environmental Scientist | C19: Science | D19: 60 | E19: 80 | F19: 80 | G19: 70 | H19: 70 | I19: =ABS('Student Calculator'!C30-D19) -> 60 | J19: =ABS('Student Calculator'!D30-E19) -> 80 | K19: =ABS('Student Calculator'!E30-F19) -> 80 | L19: =ABS('Student Calculator'!F30-G19) -> 70 | M19: =ROUND(MAX(0, 100 - (I19*0.25 + J19*0.2 + K19*0.25 + L19*0.2)), 1) -> 35 | N19: =IF(M19>=72,"🟢 BEST FIT",IF(M19>=52,"🟡 CONSIDER","🔴 MISMATCH")) -> 🔴 MISMATCH
A20: 17 | B20: Marine Biologist | C20: Science | D20: 65 | E20: 80 | F20: 80 | G20: 70 | H20: 65 | I20: =ABS('Student Calculator'!C30-D20) -> 65 | J20: =ABS('Student Calculator'!D30-E20) -> 80 | K20: =ABS('Student Calculator'!E30-F20) -> 80 | L20: =ABS('Student Calculator'!F30-G20) -> 70 | M20: =ROUND(MAX(0, 100 - (I20*0.25 + J20*0.2 + K20*0.25 + L20*0.2)), 1) -> 33.8 | N20: =IF(M20>=72,"🟢 BEST FIT",IF(M20>=52,"🟡 CONSIDER","🔴 MISMATCH")) -> 🔴 MISMATCH
A21: 18 | B21: Astronomer/Astrophysicist | C21: Science | D21: 40 | E21: 95 | F21: 85 | G21: 55 | H21: 80 | I21: =ABS('Student Calculator'!C30-D21) -> 40 | J21: =ABS('Student Calculator'!D30-E21) -> 95 | K21: =ABS('Student Calculator'!E30-F21) -> 85 | L21: =ABS('Student Calculator'!F30-G21) -> 55 | M21: =ROUND(MAX(0, 100 - (I21*0.25 + J21*0.2 + K21*0.25 + L21*0.2)), 1) -> 38.8 | N21: =IF(M21>=72,"🟢 BEST FIT",IF(M21>=52,"🟡 CONSIDER","🔴 MISMATCH")) -> 🔴 MISMATCH
A22: 19 | B22: Nuclear Engineer | C22: Engineering | D22: 75 | E22: 85 | F22: 70 | G22: 55 | H22: 75 | I22: =ABS('Student Calculator'!C30-D22) -> 75 | J22: =ABS('Student Calculator'!D30-E22) -> 85 | K22: =ABS('Student Calculator'!E30-F22) -> 70 | L22: =ABS('Student Calculator'!F30-G22) -> 55 | M22: =ROUND(MAX(0, 100 - (I22*0.25 + J22*0.2 + K22*0.25 + L22*0.2)), 1) -> 35.8 | N22: =IF(M22>=72,"🟢 BEST FIT",IF(M22>=52,"🟡 CONSIDER","🔴 MISMATCH")) -> 🔴 MISMATCH
A23: 20 | B23: Aerospace Engineer | C23: Engineering | D23: 80 | E23: 85 | F23: 70 | G23: 60 | H23: 75 | I23: =ABS('Student Calculator'!C30-D23) -> 80 | J23: =ABS('Student Calculator'!D30-E23) -> 85 | K23: =ABS('Student Calculator'!E30-F23) -> 70 | L23: =ABS('Student Calculator'!F30-G23) -> 60 | M23: =ROUND(MAX(0, 100 - (I23*0.25 + J23*0.2 + K23*0.25 + L23*0.2)), 1) -> 33.5 | N23: =IF(M23>=72,"🟢 BEST FIT",IF(M23>=52,"🟡 CONSIDER","🔴 MISMATCH")) -> 🔴 MISMATCH
A24: 21 | B24: Mechanical Engineer | C24: Engineering | D24: 85 | E24: 80 | F24: 65 | G24: 55 | H24: 75 | I24: =ABS('Student Calculator'!C30-D24) -> 85 | J24: =ABS('Student Calculator'!D30-E24) -> 80 | K24: =ABS('Student Calculator'!E30-F24) -> 65 | L24: =ABS('Student Calculator'!F30-G24) -> 55 | M24: =ROUND(MAX(0, 100 - (I24*0.25 + J24*0.2 + K24*0.25 + L24*0.2)), 1) -> 35.5 | N24: =IF(M24>=72,"🟢 BEST FIT",IF(M24>=52,"🟡 CONSIDER","🔴 MISMATCH")) -> 🔴 MISMATCH
A25: 22 | B25: Civil Engineer | C25: Engineering | D25: 80 | E25: 75 | F25: 65 | G25: 55 | H25: 75 | I25: =ABS('Student Calculator'!C30-D25) -> 80 | J25: =ABS('Student Calculator'!D30-E25) -> 75 | K25: =ABS('Student Calculator'!E30-F25) -> 65 | L25: =ABS('Student Calculator'!F30-G25) -> 55 | M25: =ROUND(MAX(0, 100 - (I25*0.25 + J25*0.2 + K25*0.25 + L25*0.2)), 1) -> 37.8 | N25: =IF(M25>=72,"🟢 BEST FIT",IF(M25>=52,"🟡 CONSIDER","🔴 MISMATCH")) -> 🔴 MISMATCH
A26: 23 | B26: Chemical Engineer | C26: Engineering | D26: 70 | E26: 85 | F26: 65 | G26: 55 | H26: 75 | I26: =ABS('Student Calculator'!C30-D26) -> 70 | J26: =ABS('Student Calculator'!D30-E26) -> 85 | K26: =ABS('Student Calculator'!E30-F26) -> 65 | L26: =ABS('Student Calculator'!F30-G26) -> 55 | M26: =ROUND(MAX(0, 100 - (I26*0.25 + J26*0.2 + K26*0.25 + L26*0.2)), 1) -> 38.3 | N26: =IF(M26>=72,"🟢 BEST FIT",IF(M26>=52,"🟡 CONSIDER","🔴 MISMATCH")) -> 🔴 MISMATCH
A27: 24 | B27: Electrical Engineer | C27: Engineering | D27: 80 | E27: 80 | F27: 65 | G27: 55 | H27: 75 | I27: =ABS('Student Calculator'!C30-D27) -> 80 | J27: =ABS('Student Calculator'!D30-E27) -> 80 | K27: =ABS('Student Calculator'!E30-F27) -> 65 | L27: =ABS('Student Calculator'!F30-G27) -> 55 | M27: =ROUND(MAX(0, 100 - (I27*0.25 + J27*0.2 + K27*0.25 + L27*0.2)), 1) -> 36.8 | N27: =IF(M27>=72,"🟢 BEST FIT",IF(M27>=52,"🟡 CONSIDER","🔴 MISMATCH")) -> 🔴 MISMATCH
A28: 25 | B28: Electronics Engineer | C28: Engineering | D28: 80 | E28: 80 | F28: 65 | G28: 55 | H28: 75 | I28: =ABS('Student Calculator'!C30-D28) -> 80 | J28: =ABS('Student Calculator'!D30-E28) -> 80 | K28: =ABS('Student Calculator'!E30-F28) -> 65 | L28: =ABS('Student Calculator'!F30-G28) -> 55 | M28: =ROUND(MAX(0, 100 - (I28*0.25 + J28*0.2 + K28*0.25 + L28*0.2)), 1) -> 36.8 | N28: =IF(M28>=72,"🟢 BEST FIT",IF(M28>=52,"🟡 CONSIDER","🔴 MISMATCH")) -> 🔴 MISMATCH
A29: 26 | B29: Computer Science Engineer | C29: Technology | D29: 55 | E29: 90 | F29: 70 | G29: 45 | H29: 80 | I29: =ABS('Student Calculator'!C30-D29) -> 55 | J29: =ABS('Student Calculator'!D30-E29) -> 90 | K29: =ABS('Student Calculator'!E30-F29) -> 70 | L29: =ABS('Student Calculator'!F30-G29) -> 45 | M29: =ROUND(MAX(0, 100 - (I29*0.25 + J29*0.2 + K29*0.25 + L29*0.2)), 1) -> 41.8 | N29: =IF(M29>=72,"🟢 BEST FIT",IF(M29>=52,"🟡 CONSIDER","🔴 MISMATCH")) -> 🔴 MISMATCH
A30: 27 | B30: Software Developer | C30: Technology | D30: 45 | E30: 90 | F30: 70 | G30: 45 | H30: 80 | I30: =ABS('Student Calculator'!C30-D30) -> 45 | J30: =ABS('Student Calculator'!D30-E30) -> 90 | K30: =ABS('Student Calculator'!E30-F30) -> 70 | L30: =ABS('Student Calculator'!F30-G30) -> 45 | M30: =ROUND(MAX(0, 100 - (I30*0.25 + J30*0.2 + K30*0.25 + L30*0.2)), 1) -> 44.3 | N30: =IF(M30>=72,"🟢 BEST FIT",IF(M30>=52,"🟡 CONSIDER","🔴 MISMATCH")) -> 🔴 MISMATCH
A31: 28 | B31: Data Scientist | C31: Technology | D31: 40 | E31: 95 | F31: 75 | G31: 40 | H31: 80 | I31: =ABS('Student Calculator'!C30-D31) -> 40 | J31: =ABS('Student Calculator'!D30-E31) -> 95 | K31: =ABS('Student Calculator'!E30-F31) -> 75 | L31: =ABS('Student Calculator'!F30-G31) -> 40 | M31: =ROUND(MAX(0, 100 - (I31*0.25 + J31*0.2 + K31*0.25 + L31*0.2)), 1) -> 44.3 | N31: =IF(M31>=72,"🟢 BEST FIT",IF(M31>=52,"🟡 CONSIDER","🔴 MISMATCH")) -> 🔴 MISMATCH
A32: 29 | B32: AI/ML Engineer | C32: Technology | D32: 40 | E32: 95 | F32: 75 | G32: 40 | H32: 80 | I32: =ABS('Student Calculator'!C30-D32) -> 40 | J32: =ABS('Student Calculator'!D30-E32) -> 95 | K32: =ABS('Student Calculator'!E30-F32) -> 75 | L32: =ABS('Student Calculator'!F30-G32) -> 40 | M32: =ROUND(MAX(0, 100 - (I32*0.25 + J32*0.2 + K32*0.25 + L32*0.2)), 1) -> 44.3 | N32: =IF(M32>=72,"🟢 BEST FIT",IF(M32>=52,"🟡 CONSIDER","🔴 MISMATCH")) -> 🔴 MISMATCH
A33: 30 | B33: Cybersecurity Analyst | C33: Technology | D33: 55 | E33: 90 | F33: 70 | G33: 40 | H33: 80 | I33: =ABS('Student Calculator'!C30-D33) -> 55 | J33: =ABS('Student Calculator'!D30-E33) -> 90 | K33: =ABS('Student Calculator'!E30-F33) -> 70 | L33: =ABS('Student Calculator'!F30-G33) -> 40 | M33: =ROUND(MAX(0, 100 - (I33*0.25 + J33*0.2 + K33*0.25 + L33*0.2)), 1) -> 42.8 | N33: =IF(M33>=72,"🟢 BEST FIT",IF(M33>=52,"🟡 CONSIDER","🔴 MISMATCH")) -> 🔴 MISMATCH
A34: 31 | B34: Cloud Solutions Architect | C34: Technology | D34: 55 | E34: 85 | F34: 70 | G34: 45 | H34: 80 | I34: =ABS('Student Calculator'!C30-D34) -> 55 | J34: =ABS('Student Calculator'!D30-E34) -> 85 | K34: =ABS('Student Calculator'!E30-F34) -> 70 | L34: =ABS('Student Calculator'!F30-G34) -> 45 | M34: =ROUND(MAX(0, 100 - (I34*0.25 + J34*0.2 + K34*0.25 + L34*0.2)), 1) -> 42.8 | N34: =IF(M34>=72,"🟢 BEST FIT",IF(M34>=52,"🟡 CONSIDER","🔴 MISMATCH")) -> 🔴 MISMATCH
A35: 32 | B35: DevOps Engineer | C35: Technology | D35: 65 | E35: 85 | F35: 65 | G35: 40 | H35: 75 | I35: =ABS('Student Calculator'!C30-D35) -> 65 | J35: =ABS('Student Calculator'!D30-E35) -> 85 | K35: =ABS('Student Calculator'!E30-F35) -> 65 | L35: =ABS('Student Calculator'!F30-G35) -> 40 | M35: =ROUND(MAX(0, 100 - (I35*0.25 + J35*0.2 + K35*0.25 + L35*0.2)), 1) -> 42.5 | N35: =IF(M35>=72,"🟢 BEST FIT",IF(M35>=52,"🟡 CONSIDER","🔴 MISMATCH")) -> 🔴 MISMATCH
A36: 33 | B36: UX/UI Designer | C36: Design | D36: 70 | E36: 65 | F36: 75 | G36: 90 | H36: 70 | I36: =ABS('Student Calculator'!C30-D36) -> 70 | J36: =ABS('Student Calculator'!D30-E36) -> 65 | K36: =ABS('Student Calculator'!E30-F36) -> 75 | L36: =ABS('Student Calculator'!F30-G36) -> 90 | M36: =ROUND(MAX(0, 100 - (I36*0.25 + J36*0.2 + K36*0.25 + L36*0.2)), 1) -> 32.8 | N36: =IF(M36>=72,"🟢 BEST FIT",IF(M36>=52,"🟡 CONSIDER","🔴 MISMATCH")) -> 🔴 MISMATCH
A37: 34 | B37: Product Manager | C37: Business | D37: 65 | E37: 75 | F37: 80 | G37: 75 | H37: 85 | I37: =ABS('Student Calculator'!C30-D37) -> 65 | J37: =ABS('Student Calculator'!D30-E37) -> 75 | K37: =ABS('Student Calculator'!E30-F37) -> 80 | L37: =ABS('Student Calculator'!F30-G37) -> 75 | M37: =ROUND(MAX(0, 100 - (I37*0.25 + J37*0.2 + K37*0.25 + L37*0.2)), 1) -> 33.8 | N37: =IF(M37>=72,"🟢 BEST FIT",IF(M37>=52,"🟡 CONSIDER","🔴 MISMATCH")) -> 🔴 MISMATCH
A38: 35 | B38: Business Analyst | C38: Business | D38: 50 | E38: 85 | F38: 70 | G38: 65 | H38: 85 | I38: =ABS('Student Calculator'!C30-D38) -> 50 | J38: =ABS('Student Calculator'!D30-E38) -> 85 | K38: =ABS('Student Calculator'!E30-F38) -> 70 | L38: =ABS('Student Calculator'!F30-G38) -> 65 | M38: =ROUND(MAX(0, 100 - (I38*0.25 + J38*0.2 + K38*0.25 + L38*0.2)), 1) -> 40 | N38: =IF(M38>=72,"🟢 BEST FIT",IF(M38>=52,"🟡 CONSIDER","🔴 MISMATCH")) -> 🔴 MISMATCH
A39: 36 | B39: Actuary | C39: Finance | D39: 35 | E39: 95 | F39: 65 | G39: 35 | H39: 85 | I39: =ABS('Student Calculator'!C30-D39) -> 35 | J39: =ABS('Student Calculator'!D30-E39) -> 95 | K39: =ABS('Student Calculator'!E30-F39) -> 65 | L39: =ABS('Student Calculator'!F30-G39) -> 35 | M39: =ROUND(MAX(0, 100 - (I39*0.25 + J39*0.2 + K39*0.25 + L39*0.2)), 1) -> 49 | N39: =IF(M39>=72,"🟢 BEST FIT",IF(M39>=52,"🟡 CONSIDER","🔴 MISMATCH")) -> 🔴 MISMATCH
A40: 37 | B40: Chartered Accountant | C40: Finance | D40: 40 | E40: 90 | F40: 60 | G40: 40 | H40: 85 | I40: =ABS('Student Calculator'!C30-D40) -> 40 | J40: =ABS('Student Calculator'!D30-E40) -> 90 | K40: =ABS('Student Calculator'!E30-F40) -> 60 | L40: =ABS('Student Calculator'!F30-G40) -> 40 | M40: =ROUND(MAX(0, 100 - (I40*0.25 + J40*0.2 + K40*0.25 + L40*0.2)), 1) -> 49 | N40: =IF(M40>=72,"🟢 BEST FIT",IF(M40>=52,"🟡 CONSIDER","🔴 MISMATCH")) -> 🔴 MISMATCH
A41: 38 | B41: Investment Banker | C41: Finance | D41: 60 | E41: 80 | F41: 70 | G41: 55 | H41: 85 | I41: =ABS('Student Calculator'!C30-D41) -> 60 | J41: =ABS('Student Calculator'!D30-E41) -> 80 | K41: =ABS('Student Calculator'!E30-F41) -> 70 | L41: =ABS('Student Calculator'!F30-G41) -> 55 | M41: =ROUND(MAX(0, 100 - (I41*0.25 + J41*0.2 + K41*0.25 + L41*0.2)), 1) -> 40.5 | N41: =IF(M41>=72,"🟢 BEST FIT",IF(M41>=52,"🟡 CONSIDER","🔴 MISMATCH")) -> 🔴 MISMATCH
A42: 39 | B42: Equity Research Analyst | C42: Finance | D42: 45 | E42: 90 | F42: 70 | G42: 50 | H42: 85 | I42: =ABS('Student Calculator'!C30-D42) -> 45 | J42: =ABS('Student Calculator'!D30-E42) -> 90 | K42: =ABS('Student Calculator'!E30-F42) -> 70 | L42: =ABS('Student Calculator'!F30-G42) -> 50 | M42: =ROUND(MAX(0, 100 - (I42*0.25 + J42*0.2 + K42*0.25 + L42*0.2)), 1) -> 43.3 | N42: =IF(M42>=72,"🟢 BEST FIT",IF(M42>=52,"🟡 CONSIDER","🔴 MISMATCH")) -> 🔴 MISMATCH
A43: 40 | B43: Financial Planner | C43: Finance | D43: 55 | E43: 80 | F43: 70 | G43: 60 | H43: 80 | I43: =ABS('Student Calculator'!C30-D43) -> 55 | J43: =ABS('Student Calculator'!D30-E43) -> 80 | K43: =ABS('Student Calculator'!E30-F43) -> 70 | L43: =ABS('Student Calculator'!F30-G43) -> 60 | M43: =ROUND(MAX(0, 100 - (I43*0.25 + J43*0.2 + K43*0.25 + L43*0.2)), 1) -> 40.8 | N43: =IF(M43>=72,"🟢 BEST FIT",IF(M43>=52,"🟡 CONSIDER","🔴 MISMATCH")) -> 🔴 MISMATCH
A44: 41 | B44: Venture Capitalist | C44: Business | D44: 70 | E44: 80 | F44: 80 | G44: 65 | H44: 90 | I44: =ABS('Student Calculator'!C30-D44) -> 70 | J44: =ABS('Student Calculator'!D30-E44) -> 80 | K44: =ABS('Student Calculator'!E30-F44) -> 80 | L44: =ABS('Student Calculator'!F30-G44) -> 65 | M44: =ROUND(MAX(0, 100 - (I44*0.25 + J44*0.2 + K44*0.25 + L44*0.2)), 1) -> 33.5 | N44: =IF(M44>=72,"🟢 BEST FIT",IF(M44>=52,"🟡 CONSIDER","🔴 MISMATCH")) -> 🔴 MISMATCH
A45: 42 | B45: Entrepreneur/Startup Founder | C45: Business | D45: 85 | E45: 65 | F45: 95 | G45: 75 | H45: 85 | I45: =ABS('Student Calculator'!C30-D45) -> 85 | J45: =ABS('Student Calculator'!D30-E45) -> 65 | K45: =ABS('Student Calculator'!E30-F45) -> 95 | L45: =ABS('Student Calculator'!F30-G45) -> 75 | M45: =ROUND(MAX(0, 100 - (I45*0.25 + J45*0.2 + K45*0.25 + L45*0.2)), 1) -> 27 | N45: =IF(M45>=72,"🟢 BEST FIT",IF(M45>=52,"🟡 CONSIDER","🔴 MISMATCH")) -> 🔴 MISMATCH
A46: 43 | B46: Management Consultant | C46: Business | D46: 65 | E46: 80 | F46: 75 | G46: 70 | H46: 90 | I46: =ABS('Student Calculator'!C30-D46) -> 65 | J46: =ABS('Student Calculator'!D30-E46) -> 80 | K46: =ABS('Student Calculator'!E30-F46) -> 75 | L46: =ABS('Student Calculator'!F30-G46) -> 70 | M46: =ROUND(MAX(0, 100 - (I46*0.25 + J46*0.2 + K46*0.25 + L46*0.2)), 1) -> 35 | N46: =IF(M46>=72,"🟢 BEST FIT",IF(M46>=52,"🟡 CONSIDER","🔴 MISMATCH")) -> 🔴 MISMATCH
A47: 44 | B47: Operations Manager | C47: Business | D47: 70 | E47: 80 | F47: 65 | G47: 65 | H47: 85 | I47: =ABS('Student Calculator'!C30-D47) -> 70 | J47: =ABS('Student Calculator'!D30-E47) -> 80 | K47: =ABS('Student Calculator'!E30-F47) -> 65 | L47: =ABS('Student Calculator'!F30-G47) -> 65 | M47: =ROUND(MAX(0, 100 - (I47*0.25 + J47*0.2 + K47*0.25 + L47*0.2)), 1) -> 37.3 | N47: =IF(M47>=72,"🟢 BEST FIT",IF(M47>=52,"🟡 CONSIDER","🔴 MISMATCH")) -> 🔴 MISMATCH
A48: 45 | B48: Supply Chain Manager | C48: Business | D48: 70 | E48: 80 | F48: 65 | G48: 60 | H48: 80 | I48: =ABS('Student Calculator'!C30-D48) -> 70 | J48: =ABS('Student Calculator'!D30-E48) -> 80 | K48: =ABS('Student Calculator'!E30-F48) -> 65 | L48: =ABS('Student Calculator'!F30-G48) -> 60 | M48: =ROUND(MAX(0, 100 - (I48*0.25 + J48*0.2 + K48*0.25 + L48*0.2)), 1) -> 38.3 | N48: =IF(M48>=72,"🟢 BEST FIT",IF(M48>=52,"🟡 CONSIDER","🔴 MISMATCH")) -> 🔴 MISMATCH
A49: 46 | B49: Human Resources Manager | C49: Business | D49: 50 | E49: 70 | F49: 70 | G49: 80 | H49: 80 | I49: =ABS('Student Calculator'!C30-D49) -> 50 | J49: =ABS('Student Calculator'!D30-E49) -> 70 | K49: =ABS('Student Calculator'!E30-F49) -> 70 | L49: =ABS('Student Calculator'!F30-G49) -> 80 | M49: =ROUND(MAX(0, 100 - (I49*0.25 + J49*0.2 + K49*0.25 + L49*0.2)), 1) -> 40 | N49: =IF(M49>=72,"🟢 BEST FIT",IF(M49>=52,"🟡 CONSIDER","🔴 MISMATCH")) -> 🔴 MISMATCH
A50: 47 | B50: Marketing Manager | C50: Business | D50: 65 | E50: 65 | F50: 75 | G50: 80 | H50: 80 | I50: =ABS('Student Calculator'!C30-D50) -> 65 | J50: =ABS('Student Calculator'!D30-E50) -> 65 | K50: =ABS('Student Calculator'!E30-F50) -> 75 | L50: =ABS('Student Calculator'!F30-G50) -> 80 | M50: =ROUND(MAX(0, 100 - (I50*0.25 + J50*0.2 + K50*0.25 + L50*0.2)), 1) -> 36 | N50: =IF(M50>=72,"🟢 BEST FIT",IF(M50>=52,"🟡 CONSIDER","🔴 MISMATCH")) -> 🔴 MISMATCH
A51: 48 | B51: Brand Strategist | C51: Business | D51: 65 | E51: 60 | F51: 75 | G51: 85 | H51: 75 | I51: =ABS('Student Calculator'!C30-D51) -> 65 | J51: =ABS('Student Calculator'!D30-E51) -> 60 | K51: =ABS('Student Calculator'!E30-F51) -> 75 | L51: =ABS('Student Calculator'!F30-G51) -> 85 | M51: =ROUND(MAX(0, 100 - (I51*0.25 + J51*0.2 + K51*0.25 + L51*0.2)), 1) -> 36 | N51: =IF(M51>=72,"🟢 BEST FIT",IF(M51>=52,"🟡 CONSIDER","🔴 MISMATCH")) -> 🔴 MISMATCH
A52: 49 | B52: Digital Marketing Specialist | C52: Business | D52: 55 | E52: 65 | F52: 70 | G52: 80 | H52: 75 | I52: =ABS('Student Calculator'!C30-D52) -> 55 | J52: =ABS('Student Calculator'!D30-E52) -> 65 | K52: =ABS('Student Calculator'!E30-F52) -> 70 | L52: =ABS('Student Calculator'!F30-G52) -> 80 | M52: =ROUND(MAX(0, 100 - (I52*0.25 + J52*0.2 + K52*0.25 + L52*0.2)), 1) -> 39.8 | N52: =IF(M52>=72,"🟢 BEST FIT",IF(M52>=52,"🟡 CONSIDER","🔴 MISMATCH")) -> 🔴 MISMATCH
A53: 50 | B53: Sales Manager | C53: Business | D53: 75 | E53: 60 | F53: 75 | G53: 75 | H53: 75 | I53: =ABS('Student Calculator'!C30-D53) -> 75 | J53: =ABS('Student Calculator'!D30-E53) -> 60 | K53: =ABS('Student Calculator'!E30-F53) -> 75 | L53: =ABS('Student Calculator'!F30-G53) -> 75 | M53: =ROUND(MAX(0, 100 - (I53*0.25 + J53*0.2 + K53*0.25 + L53*0.2)), 1) -> 35.5 | N53: =IF(M53>=72,"🟢 BEST FIT",IF(M53>=52,"🟡 CONSIDER","🔴 MISMATCH")) -> 🔴 MISMATCH
A54: 51 | B54: Retail Manager | C54: Business | D54: 70 | E54: 65 | F54: 65 | G54: 70 | H54: 70 | I54: =ABS('Student Calculator'!C30-D54) -> 70 | J54: =ABS('Student Calculator'!D30-E54) -> 65 | K54: =ABS('Student Calculator'!E30-F54) -> 65 | L54: =ABS('Student Calculator'!F30-G54) -> 70 | M54: =ROUND(MAX(0, 100 - (I54*0.25 + J54*0.2 + K54*0.25 + L54*0.2)), 1) -> 39.3 | N54: =IF(M54>=72,"🟢 BEST FIT",IF(M54>=52,"🟡 CONSIDER","🔴 MISMATCH")) -> 🔴 MISMATCH
A55: 52 | B55: Lawyer/Advocate | C55: Law | D55: 55 | E55: 70 | F55: 75 | G55: 75 | H55: 85 | I55: =ABS('Student Calculator'!C30-D55) -> 55 | J55: =ABS('Student Calculator'!D30-E55) -> 70 | K55: =ABS('Student Calculator'!E30-F55) -> 75 | L55: =ABS('Student Calculator'!F30-G55) -> 75 | M55: =ROUND(MAX(0, 100 - (I55*0.25 + J55*0.2 + K55*0.25 + L55*0.2)), 1) -> 38.5 | N55: =IF(M55>=72,"🟢 BEST FIT",IF(M55>=52,"🟡 CONSIDER","🔴 MISMATCH")) -> 🔴 MISMATCH
A56: 53 | B56: Judge | C56: Law | D56: 45 | E56: 80 | F56: 70 | G56: 65 | H56: 90 | I56: =ABS('Student Calculator'!C30-D56) -> 45 | J56: =ABS('Student Calculator'!D30-E56) -> 80 | K56: =ABS('Student Calculator'!E30-F56) -> 70 | L56: =ABS('Student Calculator'!F30-G56) -> 65 | M56: =ROUND(MAX(0, 100 - (I56*0.25 + J56*0.2 + K56*0.25 + L56*0.2)), 1) -> 42.3 | N56: =IF(M56>=72,"🟢 BEST FIT",IF(M56>=52,"🟡 CONSIDER","🔴 MISMATCH")) -> 🔴 MISMATCH
A57: 54 | B57: Corporate Lawyer | C57: Law | D57: 55 | E57: 80 | F57: 75 | G57: 65 | H57: 90 | I57: =ABS('Student Calculator'!C30-D57) -> 55 | J57: =ABS('Student Calculator'!D30-E57) -> 80 | K57: =ABS('Student Calculator'!E30-F57) -> 75 | L57: =ABS('Student Calculator'!F30-G57) -> 65 | M57: =ROUND(MAX(0, 100 - (I57*0.25 + J57*0.2 + K57*0.25 + L57*0.2)), 1) -> 38.5 | N57: =IF(M57>=72,"🟢 BEST FIT",IF(M57>=52,"🟡 CONSIDER","🔴 MISMATCH")) -> 🔴 MISMATCH
A58: 55 | B58: Criminal Lawyer | C58: Law | D58: 60 | E58: 65 | F58: 75 | G58: 70 | H58: 85 | I58: =ABS('Student Calculator'!C30-D58) -> 60 | J58: =ABS('Student Calculator'!D30-E58) -> 65 | K58: =ABS('Student Calculator'!E30-F58) -> 75 | L58: =ABS('Student Calculator'!F30-G58) -> 70 | M58: =ROUND(MAX(0, 100 - (I58*0.25 + J58*0.2 + K58*0.25 + L58*0.2)), 1) -> 39.3 | N58: =IF(M58>=72,"🟢 BEST FIT",IF(M58>=52,"🟡 CONSIDER","🔴 MISMATCH")) -> 🔴 MISMATCH
A59: 56 | B59: Human Rights Lawyer | C59: Law | D59: 40 | E59: 65 | F59: 85 | G59: 70 | H59: 85 | I59: =ABS('Student Calculator'!C30-D59) -> 40 | J59: =ABS('Student Calculator'!D30-E59) -> 65 | K59: =ABS('Student Calculator'!E30-F59) -> 85 | L59: =ABS('Student Calculator'!F30-G59) -> 70 | M59: =ROUND(MAX(0, 100 - (I59*0.25 + J59*0.2 + K59*0.25 + L59*0.2)), 1) -> 41.8 | N59: =IF(M59>=72,"🟢 BEST FIT",IF(M59>=52,"🟡 CONSIDER","🔴 MISMATCH")) -> 🔴 MISMATCH
A60: 57 | B60: IAS / IPS Officer | C60: Civil Services | D60: 60 | E60: 75 | F60: 80 | G60: 70 | H60: 90 | I60: =ABS('Student Calculator'!C30-D60) -> 60 | J60: =ABS('Student Calculator'!D30-E60) -> 75 | K60: =ABS('Student Calculator'!E30-F60) -> 80 | L60: =ABS('Student Calculator'!F30-G60) -> 70 | M60: =ROUND(MAX(0, 100 - (I60*0.25 + J60*0.2 + K60*0.25 + L60*0.2)), 1) -> 36 | N60: =IF(M60>=72,"🟢 BEST FIT",IF(M60>=52,"🟡 CONSIDER","🔴 MISMATCH")) -> 🔴 MISMATCH
A61: 58 | B61: Diplomat/IFS Officer | C61: Civil Services | D61: 55 | E61: 70 | F61: 80 | G61: 70 | H61: 90 | I61: =ABS('Student Calculator'!C30-D61) -> 55 | J61: =ABS('Student Calculator'!D30-E61) -> 70 | K61: =ABS('Student Calculator'!E30-F61) -> 80 | L61: =ABS('Student Calculator'!F30-G61) -> 70 | M61: =ROUND(MAX(0, 100 - (I61*0.25 + J61*0.2 + K61*0.25 + L61*0.2)), 1) -> 38.3 | N61: =IF(M61>=72,"🟢 BEST FIT",IF(M61>=52,"🟡 CONSIDER","🔴 MISMATCH")) -> 🔴 MISMATCH
A62: 59 | B62: Policy Analyst | C62: Government | D62: 45 | E62: 85 | F62: 80 | G62: 65 | H62: 90 | I62: =ABS('Student Calculator'!C30-D62) -> 45 | J62: =ABS('Student Calculator'!D30-E62) -> 85 | K62: =ABS('Student Calculator'!E30-F62) -> 80 | L62: =ABS('Student Calculator'!F30-G62) -> 65 | M62: =ROUND(MAX(0, 100 - (I62*0.25 + J62*0.2 + K62*0.25 + L62*0.2)), 1) -> 38.8 | N62: =IF(M62>=72,"🟢 BEST FIT",IF(M62>=52,"🟡 CONSIDER","🔴 MISMATCH")) -> 🔴 MISMATCH
A63: 60 | B63: Urban Planner | C63: Government | D63: 60 | E63: 80 | F63: 75 | G63: 70 | H63: 85 | I63: =ABS('Student Calculator'!C30-D63) -> 60 | J63: =ABS('Student Calculator'!D30-E63) -> 80 | K63: =ABS('Student Calculator'!E30-F63) -> 75 | L63: =ABS('Student Calculator'!F30-G63) -> 70 | M63: =ROUND(MAX(0, 100 - (I63*0.25 + J63*0.2 + K63*0.25 + L63*0.2)), 1) -> 36.3 | N63: =IF(M63>=72,"🟢 BEST FIT",IF(M63>=52,"🟡 CONSIDER","🔴 MISMATCH")) -> 🔴 MISMATCH
A64: 61 | B64: Military Officer | C64: Defence | D64: 85 | E64: 70 | F64: 75 | G64: 65 | H64: 85 | I64: =ABS('Student Calculator'!C30-D64) -> 85 | J64: =ABS('Student Calculator'!D30-E64) -> 70 | K64: =ABS('Student Calculator'!E30-F64) -> 75 | L64: =ABS('Student Calculator'!F30-G64) -> 65 | M64: =ROUND(MAX(0, 100 - (I64*0.25 + J64*0.2 + K64*0.25 + L64*0.2)), 1) -> 33 | N64: =IF(M64>=72,"🟢 BEST FIT",IF(M64>=52,"🟡 CONSIDER","🔴 MISMATCH")) -> 🔴 MISMATCH
A65: 62 | B65: Police Officer | C65: Defence | D65: 85 | E65: 65 | F65: 70 | G65: 65 | H65: 80 | I65: =ABS('Student Calculator'!C30-D65) -> 85 | J65: =ABS('Student Calculator'!D30-E65) -> 65 | K65: =ABS('Student Calculator'!E30-F65) -> 70 | L65: =ABS('Student Calculator'!F30-G65) -> 65 | M65: =ROUND(MAX(0, 100 - (I65*0.25 + J65*0.2 + K65*0.25 + L65*0.2)), 1) -> 35.3 | N65: =IF(M65>=72,"🟢 BEST FIT",IF(M65>=52,"🟡 CONSIDER","🔴 MISMATCH")) -> 🔴 MISMATCH
A66: 63 | B66: School Teacher | C66: Education | D66: 45 | E66: 65 | F66: 80 | G66: 80 | H66: 75 | I66: =ABS('Student Calculator'!C30-D66) -> 45 | J66: =ABS('Student Calculator'!D30-E66) -> 65 | K66: =ABS('Student Calculator'!E30-F66) -> 80 | L66: =ABS('Student Calculator'!F30-G66) -> 80 | M66: =ROUND(MAX(0, 100 - (I66*0.25 + J66*0.2 + K66*0.25 + L66*0.2)), 1) -> 39.8 | N66: =IF(M66>=72,"🟢 BEST FIT",IF(M66>=52,"🟡 CONSIDER","🔴 MISMATCH")) -> 🔴 MISMATCH
A67: 64 | B67: Professor/Academic | C67: Education | D67: 35 | E67: 85 | F67: 85 | G67: 70 | H67: 85 | I67: =ABS('Student Calculator'!C30-D67) -> 35 | J67: =ABS('Student Calculator'!D30-E67) -> 85 | K67: =ABS('Student Calculator'!E30-F67) -> 85 | L67: =ABS('Student Calculator'!F30-G67) -> 70 | M67: =ROUND(MAX(0, 100 - (I67*0.25 + J67*0.2 + K67*0.25 + L67*0.2)), 1) -> 39 | N67: =IF(M67>=72,"🟢 BEST FIT",IF(M67>=52,"🟡 CONSIDER","🔴 MISMATCH")) -> 🔴 MISMATCH
A68: 65 | B68: Education Technology Designer | C68: Education | D68: 45 | E68: 75 | F68: 80 | G68: 80 | H68: 80 | I68: =ABS('Student Calculator'!C30-D68) -> 45 | J68: =ABS('Student Calculator'!D30-E68) -> 75 | K68: =ABS('Student Calculator'!E30-F68) -> 80 | L68: =ABS('Student Calculator'!F30-G68) -> 80 | M68: =ROUND(MAX(0, 100 - (I68*0.25 + J68*0.2 + K68*0.25 + L68*0.2)), 1) -> 37.8 | N68: =IF(M68>=72,"🟢 BEST FIT",IF(M68>=52,"🟡 CONSIDER","🔴 MISMATCH")) -> 🔴 MISMATCH
A69: 66 | B69: Special Educator | C69: Education | D69: 50 | E69: 65 | F69: 85 | G69: 80 | H69: 70 | I69: =ABS('Student Calculator'!C30-D69) -> 50 | J69: =ABS('Student Calculator'!D30-E69) -> 65 | K69: =ABS('Student Calculator'!E30-F69) -> 85 | L69: =ABS('Student Calculator'!F30-G69) -> 80 | M69: =ROUND(MAX(0, 100 - (I69*0.25 + J69*0.2 + K69*0.25 + L69*0.2)), 1) -> 37.3 | N69: =IF(M69>=72,"🟢 BEST FIT",IF(M69>=52,"🟡 CONSIDER","🔴 MISMATCH")) -> 🔴 MISMATCH
A70: 67 | B70: Social Worker | C70: Social | D70: 40 | E70: 60 | F70: 85 | G70: 80 | H70: 65 | I70: =ABS('Student Calculator'!C30-D70) -> 40 | J70: =ABS('Student Calculator'!D30-E70) -> 60 | K70: =ABS('Student Calculator'!E30-F70) -> 85 | L70: =ABS('Student Calculator'!F30-G70) -> 80 | M70: =ROUND(MAX(0, 100 - (I70*0.25 + J70*0.2 + K70*0.25 + L70*0.2)), 1) -> 40.8 | N70: =IF(M70>=72,"🟢 BEST FIT",IF(M70>=52,"🟡 CONSIDER","🔴 MISMATCH")) -> 🔴 MISMATCH
A71: 68 | B71: NGO Programme Manager | C71: Social | D71: 45 | E71: 65 | F71: 85 | G71: 75 | H71: 75 | I71: =ABS('Student Calculator'!C30-D71) -> 45 | J71: =ABS('Student Calculator'!D30-E71) -> 65 | K71: =ABS('Student Calculator'!E30-F71) -> 85 | L71: =ABS('Student Calculator'!F30-G71) -> 75 | M71: =ROUND(MAX(0, 100 - (I71*0.25 + J71*0.2 + K71*0.25 + L71*0.2)), 1) -> 39.5 | N71: =IF(M71>=72,"🟢 BEST FIT",IF(M71>=52,"🟡 CONSIDER","🔴 MISMATCH")) -> 🔴 MISMATCH
A72: 69 | B72: Community Development Officer | C72: Social | D72: 45 | E72: 60 | F72: 80 | G72: 75 | H72: 70 | I72: =ABS('Student Calculator'!C30-D72) -> 45 | J72: =ABS('Student Calculator'!D30-E72) -> 60 | K72: =ABS('Student Calculator'!E30-F72) -> 80 | L72: =ABS('Student Calculator'!F30-G72) -> 75 | M72: =ROUND(MAX(0, 100 - (I72*0.25 + J72*0.2 + K72*0.25 + L72*0.2)), 1) -> 41.8 | N72: =IF(M72>=72,"🟢 BEST FIT",IF(M72>=52,"🟡 CONSIDER","🔴 MISMATCH")) -> 🔴 MISMATCH
A73: 70 | B73: Counselor/Therapist | C73: Psychology | D73: 40 | E73: 65 | F73: 85 | G73: 80 | H73: 75 | I73: =ABS('Student Calculator'!C30-D73) -> 40 | J73: =ABS('Student Calculator'!D30-E73) -> 65 | K73: =ABS('Student Calculator'!E30-F73) -> 85 | L73: =ABS('Student Calculator'!F30-G73) -> 80 | M73: =ROUND(MAX(0, 100 - (I73*0.25 + J73*0.2 + K73*0.25 + L73*0.2)), 1) -> 39.8 | N73: =IF(M73>=72,"🟢 BEST FIT",IF(M73>=52,"🟡 CONSIDER","🔴 MISMATCH")) -> 🔴 MISMATCH
A74: 71 | B74: Life Coach | C74: Psychology | D74: 50 | E74: 60 | F74: 85 | G74: 80 | H74: 70 | I74: =ABS('Student Calculator'!C30-D74) -> 50 | J74: =ABS('Student Calculator'!D30-E74) -> 60 | K74: =ABS('Student Calculator'!E30-F74) -> 85 | L74: =ABS('Student Calculator'!F30-G74) -> 80 | M74: =ROUND(MAX(0, 100 - (I74*0.25 + J74*0.2 + K74*0.25 + L74*0.2)), 1) -> 38.3 | N74: =IF(M74>=72,"🟢 BEST FIT",IF(M74>=52,"🟡 CONSIDER","🔴 MISMATCH")) -> 🔴 MISMATCH
A75: 72 | B75: Graphic Designer | C75: Creative | D75: 60 | E75: 55 | F75: 80 | G75: 95 | H75: 65 | I75: =ABS('Student Calculator'!C30-D75) -> 60 | J75: =ABS('Student Calculator'!D30-E75) -> 55 | K75: =ABS('Student Calculator'!E30-F75) -> 80 | L75: =ABS('Student Calculator'!F30-G75) -> 95 | M75: =ROUND(MAX(0, 100 - (I75*0.25 + J75*0.2 + K75*0.25 + L75*0.2)), 1) -> 35 | N75: =IF(M75>=72,"🟢 BEST FIT",IF(M75>=52,"🟡 CONSIDER","🔴 MISMATCH")) -> 🔴 MISMATCH
A76: 73 | B76: Animator | C76: Creative | D76: 65 | E76: 60 | F76: 75 | G76: 95 | H76: 65 | I76: =ABS('Student Calculator'!C30-D76) -> 65 | J76: =ABS('Student Calculator'!D30-E76) -> 60 | K76: =ABS('Student Calculator'!E30-F76) -> 75 | L76: =ABS('Student Calculator'!F30-G76) -> 95 | M76: =ROUND(MAX(0, 100 - (I76*0.25 + J76*0.2 + K76*0.25 + L76*0.2)), 1) -> 34 | N76: =IF(M76>=72,"🟢 BEST FIT",IF(M76>=52,"🟡 CONSIDER","🔴 MISMATCH")) -> 🔴 MISMATCH
A77: 74 | B77: Filmmaker/Director | C77: Creative | D77: 65 | E77: 55 | F77: 85 | G77: 90 | H77: 70 | I77: =ABS('Student Calculator'!C30-D77) -> 65 | J77: =ABS('Student Calculator'!D30-E77) -> 55 | K77: =ABS('Student Calculator'!E30-F77) -> 85 | L77: =ABS('Student Calculator'!F30-G77) -> 90 | M77: =ROUND(MAX(0, 100 - (I77*0.25 + J77*0.2 + K77*0.25 + L77*0.2)), 1) -> 33.5 | N77: =IF(M77>=72,"🟢 BEST FIT",IF(M77>=52,"🟡 CONSIDER","🔴 MISMATCH")) -> 🔴 MISMATCH
A78: 75 | B78: Screenwriter | C78: Creative | D78: 35 | E78: 55 | F78: 85 | G78: 90 | H78: 65 | I78: =ABS('Student Calculator'!C30-D78) -> 35 | J78: =ABS('Student Calculator'!D30-E78) -> 55 | K78: =ABS('Student Calculator'!E30-F78) -> 85 | L78: =ABS('Student Calculator'!F30-G78) -> 90 | M78: =ROUND(MAX(0, 100 - (I78*0.25 + J78*0.2 + K78*0.25 + L78*0.2)), 1) -> 41 | N78: =IF(M78>=72,"🟢 BEST FIT",IF(M78>=52,"🟡 CONSIDER","🔴 MISMATCH")) -> 🔴 MISMATCH
A79: 76 | B79: Journalist | C79: Media | D79: 50 | E79: 65 | F79: 80 | G79: 85 | H79: 75 | I79: =ABS('Student Calculator'!C30-D79) -> 50 | J79: =ABS('Student Calculator'!D30-E79) -> 65 | K79: =ABS('Student Calculator'!E30-F79) -> 80 | L79: =ABS('Student Calculator'!F30-G79) -> 85 | M79: =ROUND(MAX(0, 100 - (I79*0.25 + J79*0.2 + K79*0.25 + L79*0.2)), 1) -> 37.5 | N79: =IF(M79>=72,"🟢 BEST FIT",IF(M79>=52,"🟡 CONSIDER","🔴 MISMATCH")) -> 🔴 MISMATCH
A80: 77 | B80: Content Creator/Influencer | C80: Media | D80: 65 | E80: 45 | F80: 80 | G80: 85 | H80: 60 | I80: =ABS('Student Calculator'!C30-D80) -> 65 | J80: =ABS('Student Calculator'!D30-E80) -> 45 | K80: =ABS('Student Calculator'!E30-F80) -> 80 | L80: =ABS('Student Calculator'!F30-G80) -> 85 | M80: =ROUND(MAX(0, 100 - (I80*0.25 + J80*0.2 + K80*0.25 + L80*0.2)), 1) -> 37.8 | N80: =IF(M80>=72,"🟢 BEST FIT",IF(M80>=52,"🟡 CONSIDER","🔴 MISMATCH")) -> 🔴 MISMATCH
A81: 78 | B81: Photographer | C81: Creative | D81: 70 | E81: 55 | F81: 80 | G81: 90 | H81: 60 | I81: =ABS('Student Calculator'!C30-D81) -> 70 | J81: =ABS('Student Calculator'!D30-E81) -> 55 | K81: =ABS('Student Calculator'!E30-F81) -> 80 | L81: =ABS('Student Calculator'!F30-G81) -> 90 | M81: =ROUND(MAX(0, 100 - (I81*0.25 + J81*0.2 + K81*0.25 + L81*0.2)), 1) -> 33.5 | N81: =IF(M81>=72,"🟢 BEST FIT",IF(M81>=52,"🟡 CONSIDER","🔴 MISMATCH")) -> 🔴 MISMATCH
A82: 79 | B82: Fashion Designer | C82: Creative | D82: 65 | E82: 55 | F82: 80 | G82: 95 | H82: 65 | I82: =ABS('Student Calculator'!C30-D82) -> 65 | J82: =ABS('Student Calculator'!D30-E82) -> 55 | K82: =ABS('Student Calculator'!E30-F82) -> 80 | L82: =ABS('Student Calculator'!F30-G82) -> 95 | M82: =ROUND(MAX(0, 100 - (I82*0.25 + J82*0.2 + K82*0.25 + L82*0.2)), 1) -> 33.8 | N82: =IF(M82>=72,"🟢 BEST FIT",IF(M82>=52,"🟡 CONSIDER","🔴 MISMATCH")) -> 🔴 MISMATCH
A83: 80 | B83: Architect | C83: Design | D83: 75 | E83: 75 | F83: 80 | G83: 90 | H83: 80 | I83: =ABS('Student Calculator'!C30-D83) -> 75 | J83: =ABS('Student Calculator'!D30-E83) -> 75 | K83: =ABS('Student Calculator'!E30-F83) -> 80 | L83: =ABS('Student Calculator'!F30-G83) -> 90 | M83: =ROUND(MAX(0, 100 - (I83*0.25 + J83*0.2 + K83*0.25 + L83*0.2)), 1) -> 28.3 | N83: =IF(M83>=72,"🟢 BEST FIT",IF(M83>=52,"🟡 CONSIDER","🔴 MISMATCH")) -> 🔴 MISMATCH
A84: 81 | B84: Interior Designer | C84: Design | D84: 70 | E84: 60 | F84: 75 | G84: 90 | H84: 70 | I84: =ABS('Student Calculator'!C30-D84) -> 70 | J84: =ABS('Student Calculator'!D30-E84) -> 60 | K84: =ABS('Student Calculator'!E30-F84) -> 75 | L84: =ABS('Student Calculator'!F30-G84) -> 90 | M84: =ROUND(MAX(0, 100 - (I84*0.25 + J84*0.2 + K84*0.25 + L84*0.2)), 1) -> 33.8 | N84: =IF(M84>=72,"🟢 BEST FIT",IF(M84>=52,"🟡 CONSIDER","🔴 MISMATCH")) -> 🔴 MISMATCH
A85: 82 | B85: Industrial Designer | C85: Design | D85: 75 | E85: 70 | F85: 75 | G85: 85 | H85: 75 | I85: =ABS('Student Calculator'!C30-D85) -> 75 | J85: =ABS('Student Calculator'!D30-E85) -> 70 | K85: =ABS('Student Calculator'!E30-F85) -> 75 | L85: =ABS('Student Calculator'!F30-G85) -> 85 | M85: =ROUND(MAX(0, 100 - (I85*0.25 + J85*0.2 + K85*0.25 + L85*0.2)), 1) -> 31.5 | N85: =IF(M85>=72,"🟢 BEST FIT",IF(M85>=52,"🟡 CONSIDER","🔴 MISMATCH")) -> 🔴 MISMATCH
A86: 83 | B86: Music Producer | C86: Creative | D86: 55 | E86: 55 | F86: 85 | G86: 95 | H86: 65 | I86: =ABS('Student Calculator'!C30-D86) -> 55 | J86: =ABS('Student Calculator'!D30-E86) -> 55 | K86: =ABS('Student Calculator'!E30-F86) -> 85 | L86: =ABS('Student Calculator'!F30-G86) -> 95 | M86: =ROUND(MAX(0, 100 - (I86*0.25 + J86*0.2 + K86*0.25 + L86*0.2)), 1) -> 35 | N86: =IF(M86>=72,"🟢 BEST FIT",IF(M86>=52,"🟡 CONSIDER","🔴 MISMATCH")) -> 🔴 MISMATCH
A87: 84 | B87: Musician/Performer | C87: Creative | D87: 55 | E87: 45 | F87: 85 | G87: 95 | H87: 55 | I87: =ABS('Student Calculator'!C30-D87) -> 55 | J87: =ABS('Student Calculator'!D30-E87) -> 45 | K87: =ABS('Student Calculator'!E30-F87) -> 85 | L87: =ABS('Student Calculator'!F30-G87) -> 95 | M87: =ROUND(MAX(0, 100 - (I87*0.25 + J87*0.2 + K87*0.25 + L87*0.2)), 1) -> 37 | N87: =IF(M87>=72,"🟢 BEST FIT",IF(M87>=52,"🟡 CONSIDER","🔴 MISMATCH")) -> 🔴 MISMATCH
A88: 85 | B88: Actor | C88: Creative | D88: 60 | E88: 40 | F88: 85 | G88: 85 | H88: 55 | I88: =ABS('Student Calculator'!C30-D88) -> 60 | J88: =ABS('Student Calculator'!D30-E88) -> 40 | K88: =ABS('Student Calculator'!E30-F88) -> 85 | L88: =ABS('Student Calculator'!F30-G88) -> 85 | M88: =ROUND(MAX(0, 100 - (I88*0.25 + J88*0.2 + K88*0.25 + L88*0.2)), 1) -> 38.8 | N88: =IF(M88>=72,"🟢 BEST FIT",IF(M88>=52,"🟡 CONSIDER","🔴 MISMATCH")) -> 🔴 MISMATCH
A89: 86 | B89: Dancer/Choreographer | C89: Creative | D89: 80 | E89: 45 | F89: 85 | G89: 90 | H89: 55 | I89: =ABS('Student Calculator'!C30-D89) -> 80 | J89: =ABS('Student Calculator'!D30-E89) -> 45 | K89: =ABS('Student Calculator'!E30-F89) -> 85 | L89: =ABS('Student Calculator'!F30-G89) -> 90 | M89: =ROUND(MAX(0, 100 - (I89*0.25 + J89*0.2 + K89*0.25 + L89*0.2)), 1) -> 31.8 | N89: =IF(M89>=72,"🟢 BEST FIT",IF(M89>=52,"🟡 CONSIDER","🔴 MISMATCH")) -> 🔴 MISMATCH
A90: 87 | B90: Author/Writer | C90: Creative | D90: 25 | E90: 65 | F90: 90 | G90: 90 | H90: 70 | I90: =ABS('Student Calculator'!C30-D90) -> 25 | J90: =ABS('Student Calculator'!D30-E90) -> 65 | K90: =ABS('Student Calculator'!E30-F90) -> 90 | L90: =ABS('Student Calculator'!F30-G90) -> 90 | M90: =ROUND(MAX(0, 100 - (I90*0.25 + J90*0.2 + K90*0.25 + L90*0.2)), 1) -> 40.3 | N90: =IF(M90>=72,"🟢 BEST FIT",IF(M90>=52,"🟡 CONSIDER","🔴 MISMATCH")) -> 🔴 MISMATCH
A91: 88 | B91: Poet | C91: Creative | D91: 25 | E91: 55 | F91: 85 | G91: 90 | H91: 55 | I91: =ABS('Student Calculator'!C30-D91) -> 25 | J91: =ABS('Student Calculator'!D30-E91) -> 55 | K91: =ABS('Student Calculator'!E30-F91) -> 85 | L91: =ABS('Student Calculator'!F30-G91) -> 90 | M91: =ROUND(MAX(0, 100 - (I91*0.25 + J91*0.2 + K91*0.25 + L91*0.2)), 1) -> 43.5 | N91: =IF(M91>=72,"🟢 BEST FIT",IF(M91>=52,"🟡 CONSIDER","🔴 MISMATCH")) -> 🔴 MISMATCH
A92: 89 | B92: Game Designer | C92: Technology | D92: 60 | E92: 70 | F92: 80 | G92: 90 | H92: 75 | I92: =ABS('Student Calculator'!C30-D92) -> 60 | J92: =ABS('Student Calculator'!D30-E92) -> 70 | K92: =ABS('Student Calculator'!E30-F92) -> 80 | L92: =ABS('Student Calculator'!F30-G92) -> 90 | M92: =ROUND(MAX(0, 100 - (I92*0.25 + J92*0.2 + K92*0.25 + L92*0.2)), 1) -> 33 | N92: =IF(M92>=72,"🟢 BEST FIT",IF(M92>=52,"🟡 CONSIDER","🔴 MISMATCH")) -> 🔴 MISMATCH
A93: 90 | B93: Professional Athlete | C93: Sports | D93: 95 | E93: 55 | F93: 80 | G93: 75 | H93: 70 | I93: =ABS('Student Calculator'!C30-D93) -> 95 | J93: =ABS('Student Calculator'!D30-E93) -> 55 | K93: =ABS('Student Calculator'!E30-F93) -> 80 | L93: =ABS('Student Calculator'!F30-G93) -> 75 | M93: =ROUND(MAX(0, 100 - (I93*0.25 + J93*0.2 + K93*0.25 + L93*0.2)), 1) -> 30.3 | N93: =IF(M93>=72,"🟢 BEST FIT",IF(M93>=52,"🟡 CONSIDER","🔴 MISMATCH")) -> 🔴 MISMATCH
A94: 91 | B94: Sports Coach | C94: Sports | D94: 85 | E94: 60 | F94: 80 | G94: 80 | H94: 75 | I94: =ABS('Student Calculator'!C30-D94) -> 85 | J94: =ABS('Student Calculator'!D30-E94) -> 60 | K94: =ABS('Student Calculator'!E30-F94) -> 80 | L94: =ABS('Student Calculator'!F30-G94) -> 80 | M94: =ROUND(MAX(0, 100 - (I94*0.25 + J94*0.2 + K94*0.25 + L94*0.2)), 1) -> 30.8 | N94: =IF(M94>=72,"🟢 BEST FIT",IF(M94>=52,"🟡 CONSIDER","🔴 MISMATCH")) -> 🔴 MISMATCH
A95: 92 | B95: Sports Physiotherapist | C95: Sports | D95: 85 | E95: 65 | F95: 75 | G95: 75 | H95: 70 | I95: =ABS('Student Calculator'!C30-D95) -> 85 | J95: =ABS('Student Calculator'!D30-E95) -> 65 | K95: =ABS('Student Calculator'!E30-F95) -> 75 | L95: =ABS('Student Calculator'!F30-G95) -> 75 | M95: =ROUND(MAX(0, 100 - (I95*0.25 + J95*0.2 + K95*0.25 + L95*0.2)), 1) -> 32 | N95: =IF(M95>=72,"🟢 BEST FIT",IF(M95>=52,"🟡 CONSIDER","🔴 MISMATCH")) -> 🔴 MISMATCH
A96: 93 | B96: Sports Manager/Agent | C96: Sports | D96: 70 | E96: 60 | F96: 75 | G96: 70 | H96: 75 | I96: =ABS('Student Calculator'!C30-D96) -> 70 | J96: =ABS('Student Calculator'!D30-E96) -> 60 | K96: =ABS('Student Calculator'!E30-F96) -> 75 | L96: =ABS('Student Calculator'!F30-G96) -> 70 | M96: =ROUND(MAX(0, 100 - (I96*0.25 + J96*0.2 + K96*0.25 + L96*0.2)), 1) -> 37.8 | N96: =IF(M96>=72,"🟢 BEST FIT",IF(M96>=52,"🟡 CONSIDER","🔴 MISMATCH")) -> 🔴 MISMATCH
A97: 94 | B97: Fitness Trainer/Nutritionist | C97: Sports | D97: 80 | E97: 60 | F97: 75 | G97: 70 | H97: 65 | I97: =ABS('Student Calculator'!C30-D97) -> 80 | J97: =ABS('Student Calculator'!D30-E97) -> 60 | K97: =ABS('Student Calculator'!E30-F97) -> 75 | L97: =ABS('Student Calculator'!F30-G97) -> 70 | M97: =ROUND(MAX(0, 100 - (I97*0.25 + J97*0.2 + K97*0.25 + L97*0.2)), 1) -> 35.3 | N97: =IF(M97>=72,"🟢 BEST FIT",IF(M97>=52,"🟡 CONSIDER","🔴 MISMATCH")) -> 🔴 MISMATCH
A98: 95 | B98: Hotel Manager | C98: Hospitality | D98: 70 | E98: 65 | F98: 70 | G98: 70 | H98: 80 | I98: =ABS('Student Calculator'!C30-D98) -> 70 | J98: =ABS('Student Calculator'!D30-E98) -> 65 | K98: =ABS('Student Calculator'!E30-F98) -> 70 | L98: =ABS('Student Calculator'!F30-G98) -> 70 | M98: =ROUND(MAX(0, 100 - (I98*0.25 + J98*0.2 + K98*0.25 + L98*0.2)), 1) -> 38 | N98: =IF(M98>=72,"🟢 BEST FIT",IF(M98>=52,"🟡 CONSIDER","🔴 MISMATCH")) -> 🔴 MISMATCH
A99: 96 | B99: Chef/Culinary Artist | C99: Hospitality | D99: 80 | E99: 55 | F99: 80 | G99: 80 | H99: 65 | I99: =ABS('Student Calculator'!C30-D99) -> 80 | J99: =ABS('Student Calculator'!D30-E99) -> 55 | K99: =ABS('Student Calculator'!E30-F99) -> 80 | L99: =ABS('Student Calculator'!F30-G99) -> 80 | M99: =ROUND(MAX(0, 100 - (I99*0.25 + J99*0.2 + K99*0.25 + L99*0.2)), 1) -> 33 | N99: =IF(M99>=72,"🟢 BEST FIT",IF(M99>=52,"🟡 CONSIDER","🔴 MISMATCH")) -> 🔴 MISMATCH
A100: 97 | B100: Event Manager | C100: Hospitality | D100: 70 | E100: 60 | F100: 75 | G100: 75 | H100: 80 | I100: =ABS('Student Calculator'!C30-D100) -> 70 | J100: =ABS('Student Calculator'!D30-E100) -> 60 | K100: =ABS('Student Calculator'!E30-F100) -> 75 | L100: =ABS('Student Calculator'!F30-G100) -> 75 | M100: =ROUND(MAX(0, 100 - (I100*0.25 + J100*0.2 + K100*0.25 + L100*0.2)), 1) -> 36.8 | N100: =IF(M100>=72,"🟢 BEST FIT",IF(M100>=52,"🟡 CONSIDER","🔴 MISMATCH")) -> 🔴 MISMATCH
...

Sheet Thresholds & Integration
A1: LOCUS — THRESHOLD LOGIC, CCFS FORMULA & SUPABASE INTEGRATION SPEC
A2: STATUS THRESHOLDS
A3: Fit Score ≥ 72 | B3: 🟢 BEST FIT — Show in top tier, highlighted | C3: Green card, shown first
A4: Fit Score 52–71 | B4: 🟡 CONSIDER — Show faded below top 3 | C4: Orange card, secondary
A5: Fit Score < 52 | B5: 🔴 MISMATCH — Filtered out / not shown | C5: Hidden or greyed out
A7: CCFS FORMULA WEIGHTS
A8: Holland RIASEC | B8: 25% weight | C8: Environment-person fit
A9: Big Five OCEAN | B9: 20% weight | C9: Persistence probability
A10: SDT Motivation | B10: 25% weight | C10: Intrinsic vs extrinsic flag
A11: Multiple Intelligence | B11: 20% weight | C11: Cognitive task alignment
A12: Career Decision-Making | B12: 10% weight | C12: Readiness stage factor
A14: SDT OVERRIDE RULE
A15: If SDT score < 50 | B15: Apply 0.85× multiplier to CCFS | C15: Risk flag: extrinsic motivation
A16: If SDT score < 35 | B16: Show warning in UI | C16: 'Your motivation appears external — explore why'
A18: SUPABASE SCHEMA
A19: Table: quiz_responses | B19: student_id, question_id, option_selected, h_score, o_score, s_score, m_score, d_score, created_at | C19: One row per question per student
A20: Table: student_profiles | B20: student_id, holland_total, ocean_total, sdt_total, mi_total, cdm_total, ccfs, adjusted_ccfs, created_at | C20: Computed after all 25 Q answered
A21: Table: career_paths | B21: career_id, name, domain, h_profile, o_profile, s_profile, m_profile, d_profile | C21: Static reference table
A22: Table: career_matches | B22: student_id, career_id, fit_score, status, rank, created_at | C22: Computed on quiz completion
A24: SUPABASE EDGE FUNCTION
A25: Trigger: | B25: On INSERT to quiz_responses where question_id = 25 | C25: Fires after final question
A26: Step 1: | B26: SELECT SUM scores grouped by student_id | C26: Aggregate all 25 answers
A27: Step 2: | B27: Normalise each theory score ÷ max × 100 | C27: Get 0-100 per theory
A28: Step 3: | B28: CCFS = H×0.25 + O×0.20 + S×0.25 + MI×0.20 + D×0.10 | C28: Weighted composite
A29: Step 4: | B29: IF SDT < 50: adjusted_ccfs = ccfs × 0.85 | C29: Apply override
A30: Step 5: | B30: For each career: fit_score = 100 − weighted delta from profile | C30: Match all 127 careers
A31: Step 6: | B31: INSERT into career_matches sorted by fit_score DESC | C31: Store results
A32: Step 7: | B32: Return top 3 (≥72), next tier (52-71) to frontend | C32: API response
A34: FRONTEND DISPLAY LOGIC
A35: Top 3 (BEST FIT) | B35: Full card, colour accent, rank 1–3 shown prominently | C35: Green border
A36: Next tier (CONSIDER) | B36: Faded card below fold, 60% opacity, swipeable | C36: Orange indicator
A37: MISMATCH | B37: Not shown unless student taps 'See all' | C37: Hidden by default
A39: API RESPONSE SHAPE
A40: JSON structure: | B40: { student_id, ccfs, adjusted_ccfs, sdt_flag: bool,
B41: top_matches: [{career_id, name, domain, fit_score, status, rank}],
B42: secondary_matches: [...], motivation_note: string }
